{"convertExcell.py": [{"creation_time": "2023-02-21 19:20:38.903108", "modified_time": "2025-02-26 19:32:46.052926", "md5": "ec4a92074fdaefcc7d691516dfdd5bc5", "location": "D:\\UniqueTcCounter\\convertExcell.py", "uptime": "2025-02-26 19:32:47.248000+05:30", "id": "1YcYIJCGAgBjRuLBE8mgWsOjaO8xZm_YR"}], "Metadata.json": [{"creation_time": "2023-02-21 19:20:38.903108", "modified_time": "2025-02-26 19:32:57.278726", "md5": "444b09a6f84284719e4ef042878ccc3d", "location": "D:\\UniqueTcCounter\\Metadata.json", "uptime": "2025-02-26 19:32:58.354000+05:30", "id": "1Vz6nRMQIWVVPcAsrTfEKLXymDQkPnZcD"}], "Processed_20221117_170149.xlsx": [{"creation_time": "2023-02-21 19:20:38.903108", "modified_time": "2025-02-26 19:33:08.922033", "md5": "75778c6d7fa3995cf855f1e8d38d4e98", "location": "D:\\UniqueTcCounter\\Processed_20221117_170149.xlsx", "uptime": "2025-02-26 19:33:10.406000+05:30", "id": "15StIxR12RI16iKuHufD2dfcKwO4pYNMK"}], "Processed_20221117_170525.xlsx": [{"creation_time": "2023-02-21 19:20:38.903108", "modified_time": "2025-02-26 19:33:19.949795", "md5": "e37802dc3d9ceb43d76dc0894c58adaf", "location": "D:\\UniqueTcCounter\\Processed_20221117_170525.xlsx", "uptime": "2025-02-26 19:33:21.208000+05:30", "id": "1byKl8BDRHjaCE5G0nAHiIVZgTb45NCLf"}], "Processed_20221117_171052.xlsx": [{"creation_time": "2023-02-21 19:20:38.903108", "modified_time": "2025-02-26 19:33:31.349638", "md5": "f91364c9513dbaa58ef5157ea7276d09", "location": "D:\\UniqueTcCounter\\Processed_20221117_171052.xlsx", "uptime": "2025-02-26 19:33:32.582000+05:30", "id": "1LIHoItDwavl1T2l1ADOFIGKqR9ulZ83j"}], "Readme.md": [{"creation_time": "2023-02-21 19:20:38.918730", "modified_time": "2025-02-26 19:33:42.480749", "md5": "18f5326b782d466388f0b402b327bc4a", "location": "D:\\UniqueTcCounter\\Readme.md", "uptime": "2025-02-26 19:33:43.732000+05:30", "id": "1ddBJJU9dLfuHnYyEMGT8rl9jueqZmfv9"}]}